MANIFEST.in
README.rst
setup.py
factorial1034809890.egg-info/PKG-INFO
factorial1034809890.egg-info/SOURCES.txt
factorial1034809890.egg-info/dependency_links.txt
factorial1034809890.egg-info/top_level.txt
myfact/__init__.py
myfact/fact.py