Metadata-Version: 1.0
Name: factorial1034809890
Version: 0.1
Summary: Factorial Module. 
Home-page: https://www.shiyanlou.com/courses/596
Author: Nathan_Hu
Author-email: abc@icloud.com
License: MIT
Platform: Linux
